flow/record/__init__.py
flow/record/base.py
flow/record/exceptions.py
flow/record/jsonpacker.py
flow/record/packer.py
flow/record/selector.py
flow/record/stream.py
flow/record/utils.py
flow/record/version.py
flow/record/whitelist.py
flow/record/adapter/__init__.py
flow/record/adapter/archive.py
flow/record/adapter/avro.py
flow/record/adapter/broker.py
flow/record/adapter/csvfile.py
flow/record/adapter/duckdb.py
flow/record/adapter/elastic.py
flow/record/adapter/jsonfile.py
flow/record/adapter/line.py
flow/record/adapter/mongo.py
flow/record/adapter/split.py
flow/record/adapter/splunk.py
flow/record/adapter/sqlite.py
flow/record/adapter/stream.py
flow/record/adapter/text.py
flow/record/adapter/xlsx.py
flow/record/fieldtypes/__init__.py
flow/record/fieldtypes/credential.py
flow/record/fieldtypes/net/__init__.py
flow/record/fieldtypes/net/ip.py
flow/record/fieldtypes/net/ipv4.py
flow/record/fieldtypes/net/tcp.py
flow/record/fieldtypes/net/udp.py
flow/record/tools/__init__.py
flow/record/tools/geoip.py
flow/record/tools/rdump.py
flow_record-3.20.dist-info/licenses/COPYRIGHT
flow_record-3.20.dist-info/licenses/LICENSE
flow_record-3.20.dist-info/METADATA
flow_record-3.20.dist-info/WHEEL
flow_record-3.20.dist-info/entry_points.txt
flow_record-3.20.dist-info/top_level.txt
flow_record-3.20.dist-info/RECORD
